rstring_gen/__init__.py
rstring_gen-0.0.2.dist-info/LICENSE.txt
rstring_gen-0.0.2.dist-info/METADATA
rstring_gen-0.0.2.dist-info/WHEEL
rstring_gen-0.0.2.dist-info/top_level.txt
rstring_gen-0.0.2.dist-info/RECORD
