Metadata-Version: 2.1
Name: rstring-gen
Version: 0.0.2
Summary: Generates random string of given length.
Home-page: https://github.com/whatiskeptiname/rstring-gen.git
Author: Susan Ghimire
Author-email: susangmree@gmail.com
License: UNKNOWN
Platform: UNKNOWN
Classifier: Development Status :: 1 - Planning
Classifier: Programming Language :: Python :: 3
Classifier: License :: OSI Approved :: MIT License
Classifier: Operating System :: OS Independent
License-File: LICENSE.txt
